adafruit_button/__init__.py
adafruit_button/button.py
adafruit_button/button_base.py
adafruit_button/sprite_button.py
adafruit_circuitpython_display_button-1.11.6.dist-info/licenses/LICENSE
adafruit_circuitpython_display_button-1.11.6.dist-info/METADATA
adafruit_circuitpython_display_button-1.11.6.dist-info/WHEEL
adafruit_circuitpython_display_button-1.11.6.dist-info/top_level.txt
adafruit_circuitpython_display_button-1.11.6.dist-info/RECORD
