Metadata-Version: 2.4
Name: adafruit-circuitpython-display_button
Version: 1.11.6
Summary: UI Buttons for displayio
Author-email: Adafruit Industries <circuitpython@adafruit.com>
License: MIT
Project-URL: Homepage, https://github.com/adafruit/Adafruit_CircuitPython_Display_Button
Keywords: adafruit,blinka,circuitpython,micropython,display_button,buttons,UI
Classifier: Intended Audience :: Developers
Classifier: Topic :: Software Development :: Libraries
Classifier: Topic :: Software Development :: Embedded Systems
Classifier: Topic :: System :: Hardware
Classifier: License :: OSI Approved :: MIT License
Classifier: Programming Language :: Python :: 3
License-File: LICENSE
Requires-Dist: Adafruit-Blinka-displayio
Requires-Dist: Adafruit-Blinka
Requires-Dist: adafruit-circuitpython-bitmap-font
Requires-Dist: adafruit-circuitpython-display-text
Requires-Dist: adafruit-circuitpython-display-shapes
Provides-Extra: optional
Requires-Dist: adafruit-circuitpython-ImageLoad; extra == "optional"
Dynamic: license-file
